[{"id":0,"name":"hưng","password":"123","email":"1@gmail.com","avaPath":"F:\\HK2-Nam3\\C#\\space_shooter\\Space Shooter\\bin\\Debug\\img\\avatar\\defaultAvatar.png","highestScore":0},{"id":1,"name":"hưng2","password":"123","email":"2@gmail.com","avaPath":"F:\\HK2-Nam3\\C#\\space_shooter\\Space Shooter\\bin\\Debug\\img\\avatar\\Screenshot 2024-02-01 185522.png","highestScore":0},{"id":2,"name":"hưng7","password":"123","email":"3@gmail.com","avaPath":"F:\\HK2-Nam3\\C#\\space_shooter\\Space Shooter\\bin\\Debug\\img\\avatar\\Screenshot 2024-04-12 211155.png","highestScore":0},{"id":3,"name":"123","password":"123","email":"4@gmail.com","avaPath":"F:\\HK2-Nam3\\C#\\space_shooter\\Space Shooter\\bin\\Debug\\img\\avatar\\defaultAvatar.png","highestScore":0},{"id":4,"name":"1235555","password":"123","email":"5@gmail.com","avaPath":"F:\\HK2-Nam3\\C#\\space_shooter\\Space Shooter\\bin\\Debug\\img\\avatar\\defaultAvatar.png","highestScore":0},{"id":5,"name":"hungw","password":"123333","email":"hungttalop83@gmail.com","avaPath":"F:\\HK2-Nam3\\C#\\space_shooter\\Space Shooter\\bin\\Debug\\img\\avatar\\defaultAvatar.png","highestScore":0}]